LICENSE
README.md
setup.cfg
setup.py
pg_cache_storage/__init__.py
pg_cache_storage.egg-info/PKG-INFO
pg_cache_storage.egg-info/SOURCES.txt
pg_cache_storage.egg-info/dependency_links.txt
pg_cache_storage.egg-info/requires.txt
pg_cache_storage.egg-info/top_level.txt