Metadata-Version: 2.4
Name: pg-cache-storage
Version: 1.0.4
Summary: PostgreSQL cache storage for botasaurus.
Home-page: https://github.com/omkarcloud/botasaurus
Author: Chetan Jain
Author-email: 53407137+Chetan11-dev@users.noreply.github.com
License: MIT
Keywords: postgresql,pg-cache-storage,cache,botasaurus,psycopg3
Classifier: Development Status :: 5 - Production/Stable
Classifier: Topic :: Software Development :: Libraries :: Python Modules
Classifier: License :: OSI Approved :: MIT License
Classifier: Programming Language :: Python :: 3
Classifier: Programming Language :: Python :: 3.7
Classifier: Programming Language :: Python :: 3.8
Classifier: Programming Language :: Python :: 3.9
Classifier: Programming Language :: Python :: 3.10
Classifier: Programming Language :: Python :: 3.11
Classifier: Programming Language :: Python :: 3.12
Requires-Python: >=3.7
License-File: LICENSE
Requires-Dist: psycopg[binary]
Dynamic: author
Dynamic: author-email
Dynamic: classifier
Dynamic: description
Dynamic: description-content-type
Dynamic: home-page
Dynamic: keywords
Dynamic: license
Dynamic: license-file
Dynamic: requires-dist
Dynamic: requires-python
Dynamic: summary
